{
  "project_info": {
    "project_number": "187296133409",
    "project_id": "nextdns-manager-1bcd0",
    "storage_bucket": "nextdns-manager-1bcd0.firebasestorage.app"
  },
  "client": [
    {
      "client_info": {
        "mobilesdk_app_id": "1:187296133409:android:a8418fa28e074d90790e60",
        "android_client_info": {
          "package_name": "com.doubleangels.nextdnsmanagement.gms"
        }
      },
      "oauth_client": [],
      "api_key": [
        {
          "current_key": "AIzaSyDlIrlrKYMMqwG0F_7MXOEnIYqqdImRTKU"
        }
      ],
      "services": {
        "appinvite_service": {
          "other_platform_oauth_client": []
        }
      }
    }
  ],
  "configuration_version": "1"
}